__init__.py
sica_bridge/assess/__init__.py
sica_bridge/assess/component_assessor.py
sica_bridge/assess/event_aggregator.py
sica_bridge/assets/damage_examples/abutments_wingwalls_shearkeys/ex1.png
sica_bridge/assets/damage_examples/abutments_wingwalls_shearkeys/ex2.png
sica_bridge/assets/damage_examples/abutments_wingwalls_shearkeys/meta.yaml
sica_bridge/assets/damage_examples/approaches/ex1.png
sica_bridge/assets/damage_examples/approaches/ex2.png
sica_bridge/assets/damage_examples/approaches/meta.yaml
sica_bridge/assets/damage_examples/columns/ex1.png
sica_bridge/assets/damage_examples/columns/ex2.png
sica_bridge/assets/damage_examples/columns/ex3.png
sica_bridge/assets/damage_examples/columns/ex4.png
sica_bridge/assets/damage_examples/columns/meta.yaml
sica_bridge/assets/damage_examples/joints_hinges/ex1.png
sica_bridge/assets/damage_examples/joints_hinges/ex2.png
sica_bridge/assets/damage_examples/joints_hinges/meta.yaml
sica_bridge/llm/__init__.py
sica_bridge/llm/client.py
sica_bridge/llm/openai_client.py
sica_bridge/llm/prompt_builder.py
sica_bridge/prompts/system.md
sica_bridge/prompts/components/abutments_wingwalls_shearkeys.md
sica_bridge/prompts/components/approaches.md
sica_bridge/prompts/components/columns.md
sica_bridge/prompts/components/joints_hinges.md
sica_bridge/registry/__init__.py
sica_bridge/registry/components.py
sica_bridge/resources/__init__.py
sica_bridge/resources/loader.py
sica_bridge/rubrics/abutments_wingwalls_shearkeys.yaml
sica_bridge/rubrics/approaches.yaml
sica_bridge/rubrics/columns.yaml
sica_bridge/rubrics/joints_hinges.yaml
sica_bridge/schemas/__init__.py
sica_bridge/schemas/outputs.py
sica_bridge/utils/__init__.py
sica_bridge/utils/io.py
sica_bridge-0.1.2.dist-info/licenses/LICENSE
sica_bridge-0.1.2.dist-info/METADATA
sica_bridge-0.1.2.dist-info/WHEEL
sica_bridge-0.1.2.dist-info/top_level.txt
sica_bridge-0.1.2.dist-info/RECORD
