Metadata-Version: 2.4
Name: sica-bridge
Version: 0.1.2
Summary: Structure Investigation and Condition Assessment for Bridges (post-earthquake visual inspection)
Author: Issac K.T. Pang
License: MIT
Requires-Python: >=3.10
License-File: LICENSE
Requires-Dist: pydantic>=2.0
Requires-Dist: pyyaml>=6.0
Requires-Dist: openai>=1.0.0
Requires-Dist: python-dotenv>=1.0
Provides-Extra: dev
Requires-Dist: pytest>=7.0; extra == "dev"
Requires-Dist: ruff>=0.5; extra == "dev"
Dynamic: license-file
